grbl_gamepad/__init__.py
grbl_gamepad/cli.py
grbl_gamepad/jog_controller.py
grbl_gamepad-0.3.1.dist-info/AUTHORS.rst
grbl_gamepad-0.3.1.dist-info/LICENSE
grbl_gamepad-0.3.1.dist-info/METADATA
grbl_gamepad-0.3.1.dist-info/WHEEL
grbl_gamepad-0.3.1.dist-info/entry_points.txt
grbl_gamepad-0.3.1.dist-info/top_level.txt
grbl_gamepad-0.3.1.dist-info/RECORD
