Metadata-Version: 2.1
Name: grbl-gamepad
Version: 0.3.1
Summary: Jog your GRBL-based CNC machines with a gamepad controller.
Home-page: https://github.com/DariusMontez/grbl_gamepad
Author: Darius Montez
Author-email: darius.montez@gmail.com
License: MIT license
Keywords: grbl_gamepad
Platform: UNKNOWN
Classifier: Development Status :: 2 - Pre-Alpha
Classifier: Intended Audience :: Developers
Classifier: License :: OSI Approved :: MIT License
Classifier: Natural Language :: English
Classifier: Programming Language :: Python :: 2
Classifier: Programming Language :: Python :: 2.7
Classifier: Programming Language :: Python :: 3
Classifier: Programming Language :: Python :: 3.4
Classifier: Programming Language :: Python :: 3.5
Classifier: Programming Language :: Python :: 3.6
Requires-Dist: Click (>=6.0)
Requires-Dist: pyserial (>=3.0)
Requires-Dist: easy-vector (>=0.1.0)
Requires-Dist: gamepad (>=0.1.1)
Requires-Dist: grbl-link (>=0.1.4)
